enva/__init__.py
enva/checkers.py
enva/decorators.py
enva/getters.py
enva-0.1.0.dist-info/LICENSE
enva-0.1.0.dist-info/METADATA
enva-0.1.0.dist-info/WHEEL
enva-0.1.0.dist-info/top_level.txt
enva-0.1.0.dist-info/RECORD
