Metadata-Version: 2.1
Name: enva
Version: 0.1.0
Summary: Utility tools for working with environment variables
Author: Tom Titcombe
Author-email: tom@documatic.com
License-File: LICENSE
